pySecureCryptos/__init__.py
pySecureCryptos/aesWrapper.py
pySecureCryptos/aesWrapper_v2.py
pySecureCryptos/encoderDecoders.py
pySecureCryptos/fernetWrapper.py
pySecureCryptos/fernet_aesWrapper.py
pySecureCryptos/hashers.py
pySecureCryptos/hashers_v2.py
pySecureCryptos/onetimepadWrapper.py
pySecureCryptos/passwordChecker.py
pySecureCryptos/randomWrapper.py
pySecureCryptos/rsaWrapper.py
pySecureCryptos/rsaWrapper_v2.py
pySecureCryptos/server_client_encryptor.py
pySecureCryptos/server_client_encryptor_v2.py
pySecureCryptos/shuffler.py
pySecureCryptos/verifier_fernetWrapper.py
pySecureCryptos/verifier_fernetWrapper_v2.py
pySecureCryptos/verifier_fernetWrapper_v2_2.py
pySecureCryptos/verifier_fernetWrapper_v3.py
pySecureCryptos/verifier_onetimepadWrapper.py
pySecureCryptos/version.py
pySecureCryptos-0.54.dist-info/LICENSE
pySecureCryptos-0.54.dist-info/LICENSE.txt
pySecureCryptos-0.54.dist-info/METADATA
pySecureCryptos-0.54.dist-info/WHEEL
pySecureCryptos-0.54.dist-info/top_level.txt
pySecureCryptos-0.54.dist-info/RECORD
