Metadata-Version: 2.1
Name: pySecureCryptos
Version: 0.54
Summary: All the tools for cryptography / encryption for everything including databases , files , string , containers and another security methods like hashing and true random number generators in one place.
Home-page: https://github.com/harshnative/pySecureCryptos
Author: Harsh Native
Author-email: Harshnative@gmail.com
License: UNKNOWN
Platform: UNKNOWN
Classifier: Programming Language :: Python :: 3
Classifier: License :: OSI Approved :: MIT License
Classifier: Operating System :: OS Independent
Requires-Python: >=3.8
License-File: LICENSE
License-File: LICENSE.txt
Requires-Dist: cryptography (==35.0.0)
Requires-Dist: onetimepad (==1.4)
Requires-Dist: pycryptodomex (==3.11.0)
Requires-Dist: numpy (==1.22.2)
